{
    "Package\\Execute SQL Task": {
        "Description": "Execute SQL Task",
        "SQL_state": "SELECT distinct SupplierID, CategoryID FROM [dbo].[Products_Extract]  WHERE Country = ? and UnitsInStock > ?",
        "Variables": [
            [
                "User::Ship_country",
                "User::Unit_stock"
            ]
        ],
        "Result_variable": "User::res_set"
    },
    "Package\\Foreach Loop Container": {
        "Description": "Foreach Loop Container",
        "Input_variable": "User::res_set",
        "Iterr_variables": [
            [
                "User::OrderID",
                0
            ],
            [
                "User::Cat_id",
                1
            ]
        ],
        "SQL": {
            "Package\\Foreach Loop Container\\Execute SQL Task 1": {
                "Description": "Execute SQL Task",
                "SQL_state": "INSERT INTO Order_write(OrderID, Dateloop,Cat_ID) VALUES(?, GETDATE(),?)\n",
                "Variables": [
                    [
                        "User::OrderID",
                        "User::Cat_id"
                    ]
                ]
            }
        }
    }
}